{
  "meta": {
    "totalWords": 137,
    "totalLessons": 13,
    "languages": [
      "es",
      "en",
      "de",
      "pt",
      "ru",
      "ruRom",
      "zh",
      "zhPinyin"
    ],
    "lastUpdated": "2025-07-30T20:59:28.626Z",
    "generatedBy": "build-lesson-vocabulary.mjs v1.0"
  },
  "words": [
    {
      "id": "trabajador-worker",
      "es": "trabajador",
      "en": "worker",
      "de": "Arbeiter",
      "pt": "trabalhador",
      "ru": "рабочий",
      "ruRom": "rabóchiy",
      "zh": "工人",
      "zhPinyin": "gōngrén",
      "zhStrokes": "7",
      "zhRadical": "工 (trabajo)",
      "zhStructure": "izquierda-derecha",
      "category": "sustantivo",
      "source": "dia-00-fundamentos-basicos",
      "day": 0,
      "title": "Fundamentos Básicos - Conceptos Gramaticales",
      "filePath": "src/content/blog/dia-00-fundamentos-basicos.md",
      "lessons": [
        0,
        6,
        11
      ],
      "frequency": 3,
      "firstAppearance": 0
    },
    {
      "id": "lucha-struggle",
      "es": "lucha",
      "en": "struggle",
      "de": "Kampf",
      "pt": "luta",
      "ru": "борьба",
      "ruRom": "bor'bá",
      "zh": "斗争",
      "zhPinyin": "dòuzhēng",
      "zhStrokes": "12",
      "zhRadical": "斗 (lucha)",
      "zhStructure": "independiente",
      "category": "sustantivo",
      "source": "dia-00-fundamentos-basicos",
      "day": 0,
      "title": "Fundamentos Básicos - Conceptos Gramaticales",
      "filePath": "src/content/blog/dia-00-fundamentos-basicos.md",
      "lessons": [
        0,
        3,
        4,
        5,
        8,
        10,
        11
      ],
      "frequency": 7,
      "firstAppearance": 0
    },
    {
      "id": "libertad-freedom",
      "es": "libertad",
      "en": "freedom",
      "de": "Freiheit",
      "pt": "liberdade",
      "ru": "свобода",
      "ruRom": "svobóda",
      "zh": "自由",
      "zhPinyin": "zìyóu",
      "zhStrokes": "11",
      "zhRadical": "自 (uno mismo)",
      "zhStructure": "arriba-abajo",
      "category": "sustantivo",
      "source": "dia-00-fundamentos-basicos",
      "day": 0,
      "title": "Fundamentos Básicos - Conceptos Gramaticales",
      "filePath": "src/content/blog/dia-00-fundamentos-basicos.md",
      "lessons": [
        0,
        4,
        5,
        8,
        9
      ],
      "frequency": 5,
      "firstAppearance": 0
    },
    {
      "id": "pueblo-people",
      "es": "pueblo",
      "en": "people",
      "de": "Volk",
      "pt": "povo",
      "ru": "народ",
      "ruRom": "naród",
      "zh": "人民",
      "zhPinyin": "rénmín",
      "zhStrokes": "7",
      "zhRadical": "人 (persona)",
      "zhStructure": "izquierda-derecha",
      "category": "sustantivo",
      "source": "dia-00-fundamentos-basicos",
      "day": 0,
      "title": "Fundamentos Básicos - Conceptos Gramaticales",
      "filePath": "src/content/blog/dia-00-fundamentos-basicos.md",
      "lessons": [
        0,
        3,
        5,
        6,
        7,
        8,
        9,
        10,
        11
      ],
      "frequency": 9,
      "firstAppearance": 0
    },
    {
      "id": "poder-power",
      "es": "poder",
      "en": "power",
      "de": "Macht",
      "pt": "poder",
      "ru": "власть",
      "ruRom": "vlast'",
      "zh": "权力",
      "zhPinyin": "quánlì",
      "zhStrokes": "9",
      "zhRadical": "木 (madera)",
      "zhStructure": "izquierda-derecha",
      "category": "sustantivo",
      "source": "dia-00-fundamentos-basicos",
      "day": 0,
      "title": "Fundamentos Básicos - Conceptos Gramaticales",
      "filePath": "src/content/blog/dia-00-fundamentos-basicos.md",
      "lessons": [
        0
      ],
      "frequency": 1,
      "firstAppearance": 0
    },
    {
      "id": "unidad-unity",
      "es": "unidad",
      "en": "unity",
      "de": "Einheit",
      "pt": "unidade",
      "ru": "единство",
      "ruRom": "edínstvo",
      "zh": "团结",
      "zhPinyin": "tuánjié",
      "zhStrokes": "14",
      "zhRadical": "囗 (recinto)",
      "zhStructure": "izquierda-derecha",
      "category": "sustantivo",
      "source": "dia-00-fundamentos-basicos",
      "day": 0,
      "title": "Fundamentos Básicos - Conceptos Gramaticales",
      "filePath": "src/content/blog/dia-00-fundamentos-basicos.md",
      "lessons": [
        0,
        3,
        11
      ],
      "frequency": 3,
      "firstAppearance": 0
    },
    {
      "id": "bandera-flag",
      "es": "bandera",
      "en": "flag",
      "de": "Fahne",
      "pt": "bandeira",
      "ru": "знамя",
      "ruRom": "známya",
      "zh": "旗帜",
      "zhPinyin": "qízhì",
      "zhStrokes": "14",
      "zhRadical": "方 (cuadrado)",
      "zhStructure": "izquierda-derecha",
      "category": "sustantivo",
      "source": "dia-00-fundamentos-basicos",
      "day": 0,
      "title": "Fundamentos Básicos - Conceptos Gramaticales",
      "filePath": "src/content/blog/dia-00-fundamentos-basicos.md",
      "lessons": [
        0,
        10
      ],
      "frequency": 2,
      "firstAppearance": 0
    },
    {
      "id": "luchar-fight",
      "es": "luchar",
      "en": "fight",
      "de": "kämpfen",
      "pt": "lutar",
      "ru": "бороться",
      "ruRom": "borót'sya",
      "zh": "战斗",
      "zhPinyin": "zhàndòu",
      "zhStrokes": "16",
      "zhRadical": "戈 (lanza)",
      "zhStructure": "izquierda-derecha",
      "category": "verbo",
      "source": "dia-00-fundamentos-basicos",
      "day": 0,
      "title": "Fundamentos Básicos - Conceptos Gramaticales",
      "filePath": "src/content/blog/dia-00-fundamentos-basicos.md",
      "lessons": [
        0
      ],
      "frequency": 1,
      "firstAppearance": 0
    },
    {
      "id": "resistir-resist",
      "es": "resistir",
      "en": "resist",
      "de": "widerstehen",
      "pt": "resistir",
      "ru": "сопротивляться",
      "ruRom": "soprotivlyát'sya",
      "zh": "反抗",
      "zhPinyin": "fǎnkàng",
      "zhStrokes": "11",
      "zhRadical": "反 (oponer)",
      "zhStructure": "izquierda-derecha",
      "category": "verbo",
      "source": "dia-00-fundamentos-basicos",
      "day": 0,
      "title": "Fundamentos Básicos - Conceptos Gramaticales",
      "filePath": "src/content/blog/dia-00-fundamentos-basicos.md",
      "lessons": [
        0
      ],
      "frequency": 1,
      "firstAppearance": 0
    },
    {
      "id": "defender-defend",
      "es": "defender",
      "en": "defend",
      "de": "verteidigen",
      "pt": "defender",
      "ru": "защищать",
      "ruRom": "zashchishchát'",
      "zh": "捍卫",
      "zhPinyin": "hànwèi",
      "zhStrokes": "15",
      "zhRadical": "扌 (mano)",
      "zhStructure": "izquierda-derecha",
      "category": "verbo",
      "source": "dia-00-fundamentos-basicos",
      "day": 0,
      "title": "Fundamentos Básicos - Conceptos Gramaticales",
      "filePath": "src/content/blog/dia-00-fundamentos-basicos.md",
      "lessons": [
        0
      ],
      "frequency": 1,
      "firstAppearance": 0
    },
    {
      "id": "cantar-sing",
      "es": "cantar",
      "en": "sing",
      "de": "singen",
      "pt": "cantar",
      "ru": "петь",
      "ruRom": "pet'",
      "zh": "唱",
      "zhPinyin": "chàng",
      "zhStrokes": "11",
      "zhRadical": "口 (boca)",
      "zhStructure": "izquierda-derecha",
      "category": "verbo",
      "source": "dia-00-fundamentos-basicos",
      "day": 0,
      "title": "Fundamentos Básicos - Conceptos Gramaticales",
      "filePath": "src/content/blog/dia-00-fundamentos-basicos.md",
      "lessons": [
        0
      ],
      "frequency": 1,
      "firstAppearance": 0
    },
    {
      "id": "marchar-march",
      "es": "marchar",
      "en": "march",
      "de": "marschieren",
      "pt": "marchar",
      "ru": "маршировать",
      "ruRom": "marshirovat'",
      "zh": "行进",
      "zhPinyin": "xíngjìn",
      "zhStrokes": "13",
      "zhRadical": "行 (caminar)",
      "zhStructure": "izquierda-derecha",
      "category": "verbo",
      "source": "dia-00-fundamentos-basicos",
      "day": 0,
      "title": "Fundamentos Básicos - Conceptos Gramaticales",
      "filePath": "src/content/blog/dia-00-fundamentos-basicos.md",
      "lessons": [
        0
      ],
      "frequency": 1,
      "firstAppearance": 0
    },
    {
      "id": "negras-black",
      "es": "Negras",
      "en": "black",
      "de": "schwarze",
      "pt": "negras",
      "ru": "чёрные",
      "ruRom": "chyórnye",
      "zh": "黑色的",
      "zhPinyin": "hēisè de",
      "zhStrokes": "12",
      "zhRadical": "黑 (negro)",
      "zhStructure": "arriba-abajo",
      "category": "adjetivo",
      "source": "dia-01-a-las-barricadas",
      "day": 1,
      "title": "A las Barricadas",
      "filePath": "src/content/blog/dia-01-a-las-barricadas.md",
      "lessons": [
        1
      ],
      "frequency": 1,
      "firstAppearance": 1
    },
    {
      "id": "tormentas-storms",
      "es": "tormentas",
      "en": "storms",
      "de": "Stürme",
      "pt": "tempestades",
      "ru": "бури",
      "ruRom": "búri",
      "zh": "风暴",
      "zhPinyin": "fēng bào",
      "zhStrokes": "13",
      "zhRadical": "风 (viento)",
      "zhStructure": "independiente",
      "category": "sustantivo",
      "source": "dia-01-a-las-barricadas",
      "day": 1,
      "title": "A las Barricadas",
      "filePath": "src/content/blog/dia-01-a-las-barricadas.md",
      "lessons": [
        1
      ],
      "frequency": 1,
      "firstAppearance": 1
    },
    {
      "id": "agitan-shake",
      "es": "agitan",
      "en": "shake",
      "de": "schütteln",
      "pt": "agitam",
      "ru": "колышут",
      "ruRom": "kolýshut",
      "zh": "摇撼",
      "zhPinyin": "yáohàn",
      "zhStrokes": "14",
      "zhRadical": "扌 (mano)",
      "zhStructure": "izquierda-derecha",
      "category": "verbo",
      "source": "dia-01-a-las-barricadas",
      "day": 1,
      "title": "A las Barricadas",
      "filePath": "src/content/blog/dia-01-a-las-barricadas.md",
      "lessons": [
        1
      ],
      "frequency": 1,
      "firstAppearance": 1
    },
    {
      "id": "aires-skies",
      "es": "aires",
      "en": "skies",
      "de": "Lüfte",
      "pt": "ares",
      "ru": "небеса",
      "ruRom": "nebésa",
      "zh": "天空",
      "zhPinyin": "tiānkōng",
      "zhStrokes": "12",
      "zhRadical": "天 (cielo)",
      "zhStructure": "arriba-abajo",
      "category": "sustantivo",
      "source": "dia-01-a-las-barricadas",
      "day": 1,
      "title": "A las Barricadas",
      "filePath": "src/content/blog/dia-01-a-las-barricadas.md",
      "lessons": [
        1
      ],
      "frequency": 1,
      "firstAppearance": 1
    },
    {
      "id": "aunque-though",
      "es": "aunque",
      "en": "though",
      "de": "auch wenn",
      "pt": "embora",
      "ru": "хоть",
      "ruRom": "khot'",
      "zh": "虽然",
      "zhPinyin": "suīrán",
      "zhStrokes": "9",
      "zhRadical": "虫 (insecto)",
      "zhStructure": "izquierda-derecha",
      "category": "conjunción",
      "source": "dia-01-a-las-barricadas",
      "day": 1,
      "title": "A las Barricadas",
      "filePath": "src/content/blog/dia-01-a-las-barricadas.md",
      "lessons": [
        1
      ],
      "frequency": 1,
      "firstAppearance": 1
    },
    {
      "id": "espere-await",
      "es": "espere",
      "en": "await",
      "de": "erwarten",
      "pt": "espere",
      "ru": "ждёт",
      "ruRom": "zhdyot",
      "zh": "等待",
      "zhPinyin": "děng dài",
      "zhStrokes": "12",
      "zhRadical": "竹 (bambú)",
      "zhStructure": "arriba-abajo",
      "category": "verbo",
      "source": "dia-01-a-las-barricadas",
      "day": 1,
      "title": "A las Barricadas",
      "filePath": "src/content/blog/dia-01-a-las-barricadas.md",
      "lessons": [
        1
      ],
      "frequency": 1,
      "firstAppearance": 1
    },
    {
      "id": "dolor-pain",
      "es": "dolor",
      "en": "pain",
      "de": "Schmerz",
      "pt": "dor",
      "ru": "боль",
      "ruRom": "bol'",
      "zh": "痛苦",
      "zhPinyin": "tòngkǔ",
      "zhStrokes": "12",
      "zhRadical": "疒 (enfermedad)",
      "zhStructure": "arriba-abajo",
      "category": "sustantivo",
      "source": "dia-01-a-las-barricadas",
      "day": 1,
      "title": "A las Barricadas",
      "filePath": "src/content/blog/dia-01-a-las-barricadas.md",
      "lessons": [
        1
      ],
      "frequency": 1,
      "firstAppearance": 1
    },
    {
      "id": "muerte-death",
      "es": "muerte",
      "en": "death",
      "de": "Tod",
      "pt": "morte",
      "ru": "смерть",
      "ruRom": "smert'",
      "zh": "死亡",
      "zhPinyin": "sǐwáng",
      "zhStrokes": "9",
      "zhRadical": "歹 (mal)",
      "zhStructure": "izquierda-derecha",
      "category": "sustantivo",
      "source": "dia-01-a-las-barricadas",
      "day": 1,
      "title": "A las Barricadas",
      "filePath": "src/content/blog/dia-01-a-las-barricadas.md",
      "lessons": [
        1,
        4
      ],
      "frequency": 2,
      "firstAppearance": 1
    },
    {
      "id": "morir-to-die",
      "es": "morir",
      "en": "to die",
      "de": "sterben",
      "pt": "morrer",
      "ru": "умирать",
      "ruRom": "umirat'",
      "zh": "死",
      "zhPinyin": "sǐ",
      "zhStrokes": "6",
      "zhRadical": "歹 (mal)",
      "zhStructure": "arriba-abajo",
      "category": "verbo",
      "source": "dia-01-a-las-barricadas",
      "day": 1,
      "title": "A las Barricadas",
      "filePath": "src/content/blog/dia-01-a-las-barricadas.md",
      "lessons": [
        1
      ],
      "frequency": 1,
      "firstAppearance": 1
    },
    {
      "id": "llama-calls",
      "es": "llama",
      "en": "calls",
      "de": "ruft",
      "pt": "chama",
      "ru": "зовёт",
      "ruRom": "zovyót",
      "zh": "召唤",
      "zhPinyin": "zhàohuàn",
      "zhStrokes": "9",
      "zhRadical": "召 (convocar)",
      "zhStructure": "arriba-abajo",
      "category": "verbo",
      "source": "dia-01-a-las-barricadas",
      "day": 1,
      "title": "A las Barricadas",
      "filePath": "src/content/blog/dia-01-a-las-barricadas.md",
      "lessons": [
        1
      ],
      "frequency": 1,
      "firstAppearance": 1
    },
    {
      "id": "deber-duty",
      "es": "deber",
      "en": "duty",
      "de": "Pflicht",
      "pt": "dever",
      "ru": "долг",
      "ruRom": "dolg",
      "zh": "职责",
      "zhPinyin": "zhízé",
      "zhStrokes": "11",
      "zhRadical": "耳 (oreja)",
      "zhStructure": "izquierda-derecha",
      "category": "sustantivo",
      "source": "dia-01-a-las-barricadas",
      "day": 1,
      "title": "A las Barricadas",
      "filePath": "src/content/blog/dia-01-a-las-barricadas.md",
      "lessons": [
        1
      ],
      "frequency": 1,
      "firstAppearance": 1
    },
    {
      "id": "anarquismo-anarchism",
      "es": "anarquismo",
      "en": "anarchism",
      "de": "Anarchismus",
      "pt": "anarquismo",
      "ru": "анархизм",
      "ruRom": "anarkhizm",
      "zh": "无政府主义",
      "zhPinyin": "wú zhèngfǔ zhǔyì",
      "zhStrokes": "24",
      "zhRadical": "无 (sin)",
      "zhStructure": "compuesto",
      "category": "sustantivo",
      "source": "dia-01-a-las-barricadas",
      "day": 1,
      "title": "A las Barricadas",
      "filePath": "src/content/blog/dia-01-a-las-barricadas.md",
      "lessons": [
        1,
        9
      ],
      "frequency": 2,
      "firstAppearance": 1
    },
    {
      "id": "autogesti-n-self-management",
      "es": "Autogestión",
      "en": "self-management",
      "de": "Selbstverwaltung",
      "pt": "autogestão",
      "ru": "самоуправление",
      "ruRom": "samoupravléniye",
      "zh": "自治管理",
      "zhPinyin": "zìzhì guǎnlǐ",
      "zhStrokes": "19",
      "zhRadical": "自 (uno mismo)",
      "zhStructure": "compuesto",
      "category": "sustantivo",
      "source": "dia-01-a-las-barricadas",
      "day": 1,
      "title": "A las Barricadas",
      "filePath": "src/content/blog/dia-01-a-las-barricadas.md",
      "lessons": [
        1
      ],
      "frequency": 1,
      "firstAppearance": 1
    },
    {
      "id": "sindicalismo-syndicalism",
      "es": "Sindicalismo",
      "en": "syndicalism",
      "de": "Syndikalismus",
      "pt": "sindicalismo",
      "ru": "синдикализм",
      "ruRom": "sindikalizm",
      "zh": "工团主义",
      "zhPinyin": "gōngtuán zhǔyì",
      "zhStrokes": "25",
      "zhRadical": "工 (trabajo)",
      "zhStructure": "compuesto",
      "category": "sustantivo",
      "source": "dia-01-a-las-barricadas",
      "day": 1,
      "title": "A las Barricadas",
      "filePath": "src/content/blog/dia-01-a-las-barricadas.md",
      "lessons": [
        1
      ],
      "frequency": 1,
      "firstAppearance": 1
    },
    {
      "id": "lev-ntate-rise-up",
      "es": "levántate",
      "en": "rise up",
      "de": "steh auf",
      "pt": "levanta-te",
      "ru": "вставай",
      "ruRom": "vstavay",
      "zh": "起来",
      "zhPinyin": "qǐlái",
      "zhStrokes": "10",
      "zhRadical": "走 (caminar)",
      "zhStructure": "arriba-abajo",
      "category": "verbo",
      "source": "dia-02-l-internationale",
      "day": 2,
      "title": "L",
      "filePath": "src/content/blog/dia-02-l-internationale.md",
      "lessons": [
        2
      ],
      "frequency": 1,
      "firstAppearance": 2
    },
    {
      "id": "hambrientos-hungry",
      "es": "hambrientos",
      "en": "hungry",
      "de": "Hungrige",
      "pt": "famintos",
      "ru": "голодные",
      "ruRom": "golodnye",
      "zh": "饥饿的",
      "zhPinyin": "jī'è de",
      "zhStrokes": "19",
      "zhRadical": "食 (comida)",
      "zhStructure": "izquierda-derecha",
      "category": "adjetivo",
      "source": "dia-02-l-internationale",
      "day": 2,
      "title": "L",
      "filePath": "src/content/blog/dia-02-l-internationale.md",
      "lessons": [
        2
      ],
      "frequency": 1,
      "firstAppearance": 2
    },
    {
      "id": "malditos-damned",
      "es": "malditos",
      "en": "damned",
      "de": "Verdammte",
      "pt": "malditos",
      "ru": "проклятые",
      "ruRom": "proklyatye",
      "zh": "受诅咒的",
      "zhPinyin": "shòu zǔzhòu de",
      "zhStrokes": "25",
      "zhRadical": "示 (sagrado)",
      "zhStructure": "compuesto",
      "category": "adjetivo",
      "source": "dia-02-l-internationale",
      "day": 2,
      "title": "L",
      "filePath": "src/content/blog/dia-02-l-internationale.md",
      "lessons": [
        2
      ],
      "frequency": 1,
      "firstAppearance": 2
    },
    {
      "id": "esclavos-slaves",
      "es": "esclavos",
      "en": "slaves",
      "de": "Sklaven",
      "pt": "escravos",
      "ru": "рабы",
      "ruRom": "raby",
      "zh": "奴隶",
      "zhPinyin": "núlì",
      "zhStrokes": "8",
      "zhRadical": "女 (mujer)",
      "zhStructure": "izquierda-derecha",
      "category": "sustantivo",
      "source": "dia-02-l-internationale",
      "day": 2,
      "title": "L",
      "filePath": "src/content/blog/dia-02-l-internationale.md",
      "lessons": [
        2
      ],
      "frequency": 1,
      "firstAppearance": 2
    },
    {
      "id": "sangre-blood",
      "es": "sangre",
      "en": "blood",
      "de": "Blut",
      "pt": "sangue",
      "ru": "кровь",
      "ruRom": "krov'",
      "zh": "血液",
      "zhPinyin": "xuèyè",
      "zhStrokes": "12",
      "zhRadical": "血 (sangre)",
      "zhStructure": "independiente",
      "category": "sustantivo",
      "source": "dia-02-l-internationale",
      "day": 2,
      "title": "L",
      "filePath": "src/content/blog/dia-02-l-internationale.md",
      "lessons": [
        2
      ],
      "frequency": 1,
      "firstAppearance": 2
    },
    {
      "id": "hierve-boils",
      "es": "hierve",
      "en": "boils",
      "de": "kocht",
      "pt": "ferve",
      "ru": "кипит",
      "ruRom": "kipit",
      "zh": "沸腾",
      "zhPinyin": "fèi téng",
      "zhStrokes": "16",
      "zhRadical": "水 (agua)",
      "zhStructure": "izquierda-derecha",
      "category": "verbo",
      "source": "dia-02-l-internationale",
      "day": 2,
      "title": "L",
      "filePath": "src/content/blog/dia-02-l-internationale.md",
      "lessons": [
        2
      ],
      "frequency": 1,
      "firstAppearance": 2
    },
    {
      "id": "raz-n-reason",
      "es": "razón",
      "en": "reason",
      "de": "Vernunft",
      "pt": "razão",
      "ru": "разум",
      "ruRom": "razum",
      "zh": "理性",
      "zhPinyin": "lǐxìng",
      "zhStrokes": "15",
      "zhRadical": "王 (rey)",
      "zhStructure": "izquierda-derecha",
      "category": "sustantivo",
      "source": "dia-02-l-internationale",
      "day": 2,
      "title": "L",
      "filePath": "src/content/blog/dia-02-l-internationale.md",
      "lessons": [
        2
      ],
      "frequency": 1,
      "firstAppearance": 2
    },
    {
      "id": "luchar-to-fight",
      "es": "luchar",
      "en": "to fight",
      "de": "kämpfen",
      "pt": "lutar",
      "ru": "бороться",
      "ruRom": "borot'sya",
      "zh": "战斗",
      "zhPinyin": "zhàndòu",
      "zhStrokes": "16",
      "zhRadical": "戈 (arma)",
      "zhStructure": "izquierda-derecha",
      "category": "verbo",
      "source": "dia-02-l-internationale",
      "day": 2,
      "title": "L",
      "filePath": "src/content/blog/dia-02-l-internationale.md",
      "lessons": [
        2
      ],
      "frequency": 1,
      "firstAppearance": 2
    },
    {
      "id": "mundo-world",
      "es": "mundo",
      "en": "world",
      "de": "Welt",
      "pt": "mundo",
      "ru": "мир",
      "ruRom": "mir",
      "zh": "世界",
      "zhPinyin": "shìjiè",
      "zhStrokes": "9",
      "zhRadical": "世 (generación)",
      "zhStructure": "arriba-abajo",
      "category": "sustantivo",
      "source": "dia-02-l-internationale",
      "day": 2,
      "title": "L",
      "filePath": "src/content/blog/dia-02-l-internationale.md",
      "lessons": [
        2,
        6
      ],
      "frequency": 2,
      "firstAppearance": 2
    },
    {
      "id": "nada-nothing",
      "es": "nada",
      "en": "nothing",
      "de": "nichts",
      "pt": "nada",
      "ru": "ничего",
      "ruRom": "nichego",
      "zh": "什么都没有",
      "zhPinyin": "shénme dōu méiyǒu",
      "zhStrokes": "25",
      "zhRadical": "什 (qué)",
      "zhStructure": "compuesto",
      "category": "pronombre",
      "source": "dia-02-l-internationale",
      "day": 2,
      "title": "L",
      "filePath": "src/content/blog/dia-02-l-internationale.md",
      "lessons": [
        2
      ],
      "frequency": 1,
      "firstAppearance": 2
    },
    {
      "id": "proletariado-proletariat",
      "es": "proletariado",
      "en": "proletariat",
      "de": "Proletariat",
      "pt": "proletariado",
      "ru": "пролетариат",
      "ruRom": "proletariat",
      "zh": "无产阶级",
      "zhPinyin": "wúchǎnjiējí",
      "zhStrokes": "20",
      "zhRadical": "无 (sin)",
      "zhStructure": "compuesto",
      "category": "sustantivo",
      "source": "dia-02-l-internationale",
      "day": 2,
      "title": "L",
      "filePath": "src/content/blog/dia-02-l-internationale.md",
      "lessons": [
        2
      ],
      "frequency": 1,
      "firstAppearance": 2
    },
    {
      "id": "socialismo-socialism",
      "es": "socialismo",
      "en": "socialism",
      "de": "Sozialismus",
      "pt": "socialismo",
      "ru": "социализм",
      "ruRom": "sotsializm",
      "zh": "社会主义",
      "zhPinyin": "shèhuìzhǔyì",
      "zhStrokes": "22",
      "zhRadical": "社 (sociedad)",
      "zhStructure": "compuesto",
      "category": "sustantivo",
      "source": "dia-02-l-internationale",
      "day": 2,
      "title": "L",
      "filePath": "src/content/blog/dia-02-l-internationale.md",
      "lessons": [
        2,
        7
      ],
      "frequency": 2,
      "firstAppearance": 2
    },
    {
      "id": "clase-obrera-working-class",
      "es": "clase obrera",
      "en": "working class",
      "de": "Arbeiterklasse",
      "pt": "classe operária",
      "ru": "рабочий класс",
      "ruRom": "rabochiy klass",
      "zh": "工人阶级",
      "zhPinyin": "gōngrén jiējí",
      "zhStrokes": "18",
      "zhRadical": "工 (trabajo)",
      "zhStructure": "compuesto",
      "category": "sustantivo",
      "source": "dia-02-l-internationale",
      "day": 2,
      "title": "L",
      "filePath": "src/content/blog/dia-02-l-internationale.md",
      "lessons": [
        2
      ],
      "frequency": 1,
      "firstAppearance": 2
    },
    {
      "id": "solidaridad-solidarity",
      "es": "solidaridad",
      "en": "solidarity",
      "de": "Solidarität",
      "pt": "solidariedade",
      "ru": "солидарность",
      "ruRom": "solidarnost'",
      "zh": "团结",
      "zhPinyin": "tuánjié",
      "zhStrokes": "14",
      "zhRadical": "囗 (recinto)",
      "zhStructure": "arriba-abajo",
      "category": "sustantivo",
      "source": "dia-02-l-internationale",
      "day": 2,
      "title": "L",
      "filePath": "src/content/blog/dia-02-l-internationale.md",
      "lessons": [
        2,
        9,
        11
      ],
      "frequency": 3,
      "firstAppearance": 2
    },
    {
      "id": "unido-united",
      "es": "unido",
      "en": "united",
      "de": "vereint",
      "pt": "unido",
      "ru": "единый",
      "ruRom": "edinyy",
      "zh": "团结的",
      "zhPinyin": "tuánjié de",
      "zhStrokes": "14",
      "zhRadical": "囗 (recinto)",
      "zhStructure": "izquierda-derecha",
      "category": "adjetivo",
      "source": "dia-03-el-pueblo-unido",
      "day": 3,
      "title": "El Pueblo Unido Jamás Será Vencido",
      "filePath": "src/content/blog/dia-03-el-pueblo-unido.md",
      "lessons": [
        3
      ],
      "frequency": 1,
      "firstAppearance": 3
    },
    {
      "id": "vencido-defeated",
      "es": "vencido",
      "en": "defeated",
      "de": "besiegt",
      "pt": "vencido",
      "ru": "побеждённый",
      "ruRom": "pobezhdyonnyy",
      "zh": "被战胜的",
      "zhPinyin": "bèi zhànshèng de",
      "zhStrokes": "12",
      "zhRadical": "戈 (lanza)",
      "zhStructure": "izquierda-derecha",
      "category": "adjetivo",
      "source": "dia-03-el-pueblo-unido",
      "day": 3,
      "title": "El Pueblo Unido Jamás Será Vencido",
      "filePath": "src/content/blog/dia-03-el-pueblo-unido.md",
      "lessons": [
        3
      ],
      "frequency": 1,
      "firstAppearance": 3
    },
    {
      "id": "triunfar-triumph",
      "es": "triunfar",
      "en": "triumph",
      "de": "siegen",
      "pt": "triunfar",
      "ru": "победить",
      "ruRom": "pobedit'",
      "zh": "胜利",
      "zhPinyin": "shènglì",
      "zhStrokes": "14",
      "zhRadical": "力 (fuerza)",
      "zhStructure": "izquierda-derecha",
      "category": "verbo",
      "source": "dia-03-el-pueblo-unido",
      "day": 3,
      "title": "El Pueblo Unido Jamás Será Vencido",
      "filePath": "src/content/blog/dia-03-el-pueblo-unido.md",
      "lessons": [
        3
      ],
      "frequency": 1,
      "firstAppearance": 3
    },
    {
      "id": "jam-s-never",
      "es": "jamás",
      "en": "never",
      "de": "niemals",
      "pt": "jamais",
      "ru": "никогда",
      "ruRom": "nikogda",
      "zh": "永远不会",
      "zhPinyin": "yǒngyuǎn bù huì",
      "zhStrokes": "15",
      "zhRadical": "水 (agua) + 辶 (caminar)",
      "zhStructure": "compuesto",
      "category": "adverbio",
      "source": "dia-03-el-pueblo-unido",
      "day": 3,
      "title": "El Pueblo Unido Jamás Será Vencido",
      "filePath": "src/content/blog/dia-03-el-pueblo-unido.md",
      "lessons": [
        3
      ],
      "frequency": 1,
      "firstAppearance": 3
    },
    {
      "id": "ser--will-be",
      "es": "será",
      "en": "will be",
      "de": "wird sein",
      "pt": "será",
      "ru": "будет",
      "ruRom": "budet",
      "zh": "将是",
      "zhPinyin": "jiāng shì",
      "zhStrokes": "12",
      "zhRadical": "寸 (pulgada) + 日 (sol)",
      "zhStructure": "compuesto",
      "category": "verbo",
      "source": "dia-03-el-pueblo-unido",
      "day": 3,
      "title": "El Pueblo Unido Jamás Será Vencido",
      "filePath": "src/content/blog/dia-03-el-pueblo-unido.md",
      "lessons": [
        3
      ],
      "frequency": 1,
      "firstAppearance": 3
    },
    {
      "id": "marcha-march",
      "es": "marcha",
      "en": "march",
      "de": "Marsch",
      "pt": "marcha",
      "ru": "марш",
      "ruRom": "marsh",
      "zh": "行进",
      "zhPinyin": "xíngjìn",
      "zhStrokes": "13",
      "zhRadical": "行 (caminar) + 辶 (caminar)",
      "zhStructure": "compuesto",
      "category": "sustantivo",
      "source": "dia-03-el-pueblo-unido",
      "day": 3,
      "title": "El Pueblo Unido Jamás Será Vencido",
      "filePath": "src/content/blog/dia-03-el-pueblo-unido.md",
      "lessons": [
        3
      ],
      "frequency": 1,
      "firstAppearance": 3
    },
    {
      "id": "eterna-eternal",
      "es": "eterna",
      "en": "eternal",
      "de": "ewig",
      "pt": "eterna",
      "ru": "вечная",
      "ruRom": "vechnaya",
      "zh": "永恒的",
      "zhPinyin": "yǒnghéng de",
      "zhStrokes": "14",
      "zhRadical": "水 (agua) + 心 (corazón)",
      "zhStructure": "compuesto",
      "category": "adjetivo",
      "source": "dia-03-el-pueblo-unido",
      "day": 3,
      "title": "El Pueblo Unido Jamás Será Vencido",
      "filePath": "src/content/blog/dia-03-el-pueblo-unido.md",
      "lessons": [
        3
      ],
      "frequency": 1,
      "firstAppearance": 3
    },
    {
      "id": "historia-history",
      "es": "historia",
      "en": "history",
      "de": "Geschichte",
      "pt": "história",
      "ru": "история",
      "ruRom": "istoriya",
      "zh": "历史",
      "zhPinyin": "lìshǐ",
      "zhStrokes": "9",
      "zhRadical": "厂 (acantilado) + 口 (boca)",
      "zhStructure": "compuesto",
      "category": "sustantivo",
      "source": "dia-03-el-pueblo-unido",
      "day": 3,
      "title": "El Pueblo Unido Jamás Será Vencido",
      "filePath": "src/content/blog/dia-03-el-pueblo-unido.md",
      "lessons": [
        3
      ],
      "frequency": 1,
      "firstAppearance": 3
    },
    {
      "id": "vencer-to-conquer",
      "es": "vencer",
      "en": "to conquer",
      "de": "besiegen",
      "pt": "vencer",
      "ru": "победить",
      "ruRom": "pobedit'",
      "zh": "战胜",
      "zhPinyin": "zhànshèng",
      "zhStrokes": "12",
      "zhRadical": "戈 (lanza)",
      "zhStructure": "izquierda-derecha",
      "category": "verbo",
      "source": "dia-03-el-pueblo-unido",
      "day": 3,
      "title": "El Pueblo Unido Jamás Será Vencido",
      "filePath": "src/content/blog/dia-03-el-pueblo-unido.md",
      "lessons": [
        3
      ],
      "frequency": 1,
      "firstAppearance": 3
    },
    {
      "id": "banderas-banners",
      "es": "banderas",
      "en": "banners",
      "de": "Fahnen",
      "pt": "bandeiras",
      "ru": "знамёна",
      "ruRom": "znamyona",
      "zh": "旗帜",
      "zhPinyin": "qízhì",
      "zhStrokes": "14",
      "zhRadical": "方 (dirección)",
      "zhStructure": "izquierda-derecha",
      "category": "sustantivo",
      "source": "dia-03-el-pueblo-unido",
      "day": 3,
      "title": "El Pueblo Unido Jamás Será Vencido",
      "filePath": "src/content/blog/dia-03-el-pueblo-unido.md",
      "lessons": [
        3
      ],
      "frequency": 1,
      "firstAppearance": 3
    },
    {
      "id": "amanecer-dawn",
      "es": "amanecer",
      "en": "dawn",
      "de": "Morgendämmerung",
      "pt": "amanhecer",
      "ru": "заря",
      "ruRom": "zarya",
      "zh": "黎明",
      "zhPinyin": "lí míng",
      "zhStrokes": "23",
      "zhRadical": "黍 (mijo) + 日 (sol)",
      "zhStructure": "compuesto",
      "category": "sustantivo",
      "source": "dia-03-el-pueblo-unido",
      "day": 3,
      "title": "El Pueblo Unido Jamás Será Vencido",
      "filePath": "src/content/blog/dia-03-el-pueblo-unido.md",
      "lessons": [
        3
      ],
      "frequency": 1,
      "firstAppearance": 3
    },
    {
      "id": "victoria-victory",
      "es": "victoria",
      "en": "victory",
      "de": "Sieg",
      "pt": "vitória",
      "ru": "победа",
      "ruRom": "pobeda",
      "zh": "胜利",
      "zhPinyin": "shènglì",
      "zhStrokes": "14",
      "zhRadical": "力 (fuerza)",
      "zhStructure": "izquierda-derecha",
      "category": "sustantivo",
      "source": "dia-03-el-pueblo-unido",
      "day": 3,
      "title": "El Pueblo Unido Jamás Será Vencido",
      "filePath": "src/content/blog/dia-03-el-pueblo-unido.md",
      "lessons": [
        3,
        5,
        8
      ],
      "frequency": 3,
      "firstAppearance": 3
    },
    {
      "id": "mil-novecientos-setenta-nineteen-seventy",
      "es": "mil novecientos setenta",
      "en": "nineteen seventy",
      "de": "neunzehnhundertsiebzig",
      "pt": "mil novecentos e setenta",
      "ru": "тысяча девятьсот семьдесят",
      "ruRom": "tysyacha devyat'sot sem'desyat",
      "zh": "一九七零年",
      "zhPinyin": "yī jiǔ qī líng nián",
      "category": "sustantivo",
      "source": "dia-03-el-pueblo-unido",
      "day": 3,
      "title": "El Pueblo Unido Jamás Será Vencido",
      "filePath": "src/content/blog/dia-03-el-pueblo-unido.md",
      "lessons": [
        3,
        4
      ],
      "frequency": 2,
      "firstAppearance": 3
    },
    {
      "id": "gale-n-galleon",
      "es": "galeón",
      "en": "galleon",
      "de": "Galeone",
      "pt": "galeão",
      "ru": "галеон",
      "ruRom": "galeon",
      "zh": "大帆船",
      "zhPinyin": "dà fānchuán",
      "zhStrokes": "12",
      "zhRadical": "船 (barco)",
      "zhStructure": "izquierda-derecha",
      "category": "sustantivo",
      "source": "dia-04-il-galeone",
      "day": 4,
      "title": "Il Galeone",
      "filePath": "src/content/blog/dia-04-il-galeone.md",
      "lessons": [
        4
      ],
      "frequency": 1,
      "firstAppearance": 4
    },
    {
      "id": "marineros-sailors",
      "es": "marineros",
      "en": "sailors",
      "de": "Seeleute",
      "pt": "marinheiros",
      "ru": "моряки",
      "ruRom": "moryaki",
      "zh": "船员",
      "zhPinyin": "chuányuán",
      "zhStrokes": "16",
      "zhRadical": "舟 (barco) + 口 (boca)",
      "zhStructure": "compuesto",
      "category": "sustantivo",
      "source": "dia-04-il-galeone",
      "day": 4,
      "title": "Il Galeone",
      "filePath": "src/content/blog/dia-04-il-galeone.md",
      "lessons": [
        4
      ],
      "frequency": 1,
      "firstAppearance": 4
    },
    {
      "id": "puerto-port",
      "es": "puerto",
      "en": "port",
      "de": "Hafen",
      "pt": "porto",
      "ru": "порт",
      "ruRom": "port",
      "zh": "港口",
      "zhPinyin": "gǎngkǒu",
      "zhStrokes": "15",
      "zhRadical": "氵 (agua) + 口 (boca)",
      "zhStructure": "compuesto",
      "category": "sustantivo",
      "source": "dia-04-il-galeone",
      "day": 4,
      "title": "Il Galeone",
      "filePath": "src/content/blog/dia-04-il-galeone.md",
      "lessons": [
        4
      ],
      "frequency": 1,
      "firstAppearance": 4
    },
    {
      "id": "viento-wind",
      "es": "viento",
      "en": "wind",
      "de": "Wind",
      "pt": "vento",
      "ru": "ветер",
      "ruRom": "veter",
      "zh": "风",
      "zhPinyin": "fēng",
      "zhStrokes": "4",
      "zhRadical": "风 (viento)",
      "zhStructure": "independiente",
      "category": "sustantivo",
      "source": "dia-04-il-galeone",
      "day": 4,
      "title": "Il Galeone",
      "filePath": "src/content/blog/dia-04-il-galeone.md",
      "lessons": [
        4
      ],
      "frequency": 1,
      "firstAppearance": 4
    },
    {
      "id": "oleada-wave",
      "es": "oleada",
      "en": "wave",
      "de": "Welle",
      "pt": "onda",
      "ru": "волна",
      "ruRom": "volna",
      "zh": "波浪",
      "zhPinyin": "bō làng",
      "zhStrokes": "10",
      "zhRadical": "氵 (agua)",
      "zhStructure": "izquierda-derecha",
      "category": "sustantivo",
      "source": "dia-04-il-galeone",
      "day": 4,
      "title": "Il Galeone",
      "filePath": "src/content/blog/dia-04-il-galeone.md",
      "lessons": [
        4
      ],
      "frequency": 1,
      "firstAppearance": 4
    },
    {
      "id": "esclavo-slave",
      "es": "esclavo",
      "en": "slave",
      "de": "Sklave",
      "pt": "escravo",
      "ru": "раб",
      "ruRom": "rab",
      "zh": "奴隶",
      "zhPinyin": "núlì",
      "zhStrokes": "12",
      "zhRadical": "女 (mujer)",
      "zhStructure": "izquierda-derecha",
      "category": "sustantivo",
      "source": "dia-04-il-galeone",
      "day": 4,
      "title": "Il Galeone",
      "filePath": "src/content/blog/dia-04-il-galeone.md",
      "lessons": [
        4
      ],
      "frequency": 1,
      "firstAppearance": 4
    },
    {
      "id": "cadenas-chains",
      "es": "cadenas",
      "en": "chains",
      "de": "Ketten",
      "pt": "correntes",
      "ru": "цепи",
      "ruRom": "tsepi",
      "zh": "锁链",
      "zhPinyin": "suǒliàn",
      "zhStrokes": "13",
      "zhRadical": "钅 (metal)",
      "zhStructure": "izquierda-derecha",
      "category": "sustantivo",
      "source": "dia-04-il-galeone",
      "day": 4,
      "title": "Il Galeone",
      "filePath": "src/content/blog/dia-04-il-galeone.md",
      "lessons": [
        4
      ],
      "frequency": 1,
      "firstAppearance": 4
    },
    {
      "id": "movimiento-movement",
      "es": "movimiento",
      "en": "movement",
      "de": "Bewegung",
      "pt": "movimento",
      "ru": "движение",
      "ruRom": "dvizhenie",
      "zh": "运动",
      "zhPinyin": "yùn dòng",
      "zhStrokes": "11",
      "zhRadical": "辶 (caminar)",
      "zhStructure": "izquierda-derecha",
      "category": "sustantivo",
      "source": "dia-04-il-galeone",
      "day": 4,
      "title": "Il Galeone",
      "filePath": "src/content/blog/dia-04-il-galeone.md",
      "lessons": [
        4
      ],
      "frequency": 1,
      "firstAppearance": 4
    },
    {
      "id": "anarqu-a-anarchy",
      "es": "anarquía",
      "en": "anarchy",
      "de": "Anarchie",
      "pt": "anarquia",
      "ru": "анархия",
      "ruRom": "anarkhiya",
      "zh": "无政府主义",
      "zhPinyin": "wú zhèngfǔ zhǔyì",
      "zhStrokes": "16",
      "zhRadical": "无 (sin)",
      "zhStructure": "compuesto",
      "category": "sustantivo",
      "source": "dia-04-il-galeone",
      "day": 4,
      "title": "Il Galeone",
      "filePath": "src/content/blog/dia-04-il-galeone.md",
      "lessons": [
        4
      ],
      "frequency": 1,
      "firstAppearance": 4
    },
    {
      "id": "partisanos-partisans",
      "es": "partisanos",
      "en": "partisans",
      "de": "Partisanen",
      "pt": "partidários",
      "ru": "партизаны",
      "ruRom": "partizany",
      "zh": "游击队",
      "zhPinyin": "yóujīduì",
      "zhStrokes": "9",
      "zhRadical": "辶 (camino)",
      "zhStructure": "semi-encierro",
      "category": "sustantivo",
      "source": "dia-05-pesn-partizan",
      "day": 5,
      "title": "Песнь Партизан / Le Chant des Partisans",
      "filePath": "src/content/blog/dia-05-pesn-partizan.md",
      "lessons": [
        5
      ],
      "frequency": 1,
      "firstAppearance": 5
    },
    {
      "id": "resistencia-resistance",
      "es": "resistencia",
      "en": "resistance",
      "de": "Widerstand",
      "pt": "resistência",
      "ru": "сопротивление",
      "ruRom": "soprotivlenie",
      "zh": "抵抗",
      "zhPinyin": "dǐkàng",
      "zhStrokes": "15",
      "zhRadical": "手 (mano)",
      "zhStructure": "izquierda-derecha",
      "category": "sustantivo",
      "source": "dia-05-pesn-partizan",
      "day": 5,
      "title": "Песнь Партизан / Le Chant des Partisans",
      "filePath": "src/content/blog/dia-05-pesn-partizan.md",
      "lessons": [
        5,
        6,
        8,
        10,
        11
      ],
      "frequency": 5,
      "firstAppearance": 5
    },
    {
      "id": "guerra-war",
      "es": "guerra",
      "en": "war",
      "de": "Krieg",
      "pt": "guerra",
      "ru": "война",
      "ruRom": "voyna",
      "zh": "战争",
      "zhPinyin": "zhànzhēng",
      "zhStrokes": "16",
      "zhRadical": "戈 (lanza)",
      "zhStructure": "izquierda-derecha",
      "category": "sustantivo",
      "source": "dia-05-pesn-partizan",
      "day": 5,
      "title": "Песнь Партизан / Le Chant des Partisans",
      "filePath": "src/content/blog/dia-05-pesn-partizan.md",
      "lessons": [
        5,
        6,
        8
      ],
      "frequency": 3,
      "firstAppearance": 5
    },
    {
      "id": "soldados-soldiers",
      "es": "soldados",
      "en": "soldiers",
      "de": "Soldaten",
      "pt": "soldados",
      "ru": "солдаты",
      "ruRom": "soldaty",
      "zh": "士兵",
      "zhPinyin": "shìbīng",
      "zhStrokes": "10",
      "zhRadical": "士 (soldado)",
      "zhStructure": "arriba-abajo",
      "category": "sustantivo",
      "source": "dia-05-pesn-partizan",
      "day": 5,
      "title": "Песнь Партизан / Le Chant des Partisans",
      "filePath": "src/content/blog/dia-05-pesn-partizan.md",
      "lessons": [
        5,
        8
      ],
      "frequency": 2,
      "firstAppearance": 5
    },
    {
      "id": "monta-as-mountains",
      "es": "montañas",
      "en": "mountains",
      "de": "Berge",
      "pt": "montanhas",
      "ru": "горы",
      "ruRom": "gory",
      "zh": "山脉",
      "zhPinyin": "shānmài",
      "zhStrokes": "10",
      "zhRadical": "山 (montaña)",
      "zhStructure": "izquierda-derecha",
      "category": "sustantivo",
      "source": "dia-05-pesn-partizan",
      "day": 5,
      "title": "Песнь Партизан / Le Chant des Partisans",
      "filePath": "src/content/blog/dia-05-pesn-partizan.md",
      "lessons": [
        5
      ],
      "frequency": 1,
      "firstAppearance": 5
    },
    {
      "id": "libertadores-liberators",
      "es": "libertadores",
      "en": "liberators",
      "de": "Befreier",
      "pt": "libertadores",
      "ru": "освободители",
      "ruRom": "osvoboditeli",
      "zh": "解放者",
      "zhPinyin": "jiěfàng zhě",
      "zhStrokes": "13",
      "zhRadical": "角 (ángulo)",
      "zhStructure": "izquierda-derecha",
      "category": "sustantivo",
      "source": "dia-05-pesn-partizan",
      "day": 5,
      "title": "Песнь Партизан / Le Chant des Partisans",
      "filePath": "src/content/blog/dia-05-pesn-partizan.md",
      "lessons": [
        5
      ],
      "frequency": 1,
      "firstAppearance": 5
    },
    {
      "id": "sabotaje-sabotage",
      "es": "sabotaje",
      "en": "sabotage",
      "de": "Sabotage",
      "pt": "sabotagem",
      "ru": "диверсия",
      "ruRom": "diversiya",
      "zh": "破坏",
      "zhPinyin": "pòhuài",
      "zhStrokes": "13",
      "zhRadical": "石 (piedra)",
      "zhStructure": "izquierda-derecha",
      "category": "sustantivo",
      "source": "dia-05-pesn-partizan",
      "day": 5,
      "title": "Песнь Партизан / Le Chant des Partisans",
      "filePath": "src/content/blog/dia-05-pesn-partizan.md",
      "lessons": [
        5
      ],
      "frequency": 1,
      "firstAppearance": 5
    },
    {
      "id": "clandestino-underground",
      "es": "clandestino",
      "en": "underground",
      "de": "Untergrund",
      "pt": "clandestino",
      "ru": "подпольный",
      "ruRom": "podpol'nyy",
      "zh": "地下的",
      "zhPinyin": "dìxià de",
      "zhStrokes": "9",
      "zhRadical": "土 (tierra)",
      "zhStructure": "arriba-abajo",
      "category": "adjetivo",
      "source": "dia-05-pesn-partizan",
      "day": 5,
      "title": "Песнь Партизан / Le Chant des Partisans",
      "filePath": "src/content/blog/dia-05-pesn-partizan.md",
      "lessons": [
        5
      ],
      "frequency": 1,
      "firstAppearance": 5
    },
    {
      "id": "fascismo-fascism",
      "es": "fascismo",
      "en": "fascism",
      "de": "Faschismus",
      "pt": "fascismo",
      "ru": "фашизм",
      "ruRom": "fashizm",
      "zh": "法西斯主义",
      "zhPinyin": "fǎxīsī zhǔyì",
      "zhStrokes": "23",
      "zhRadical": "氵 (agua)",
      "zhStructure": "izquierda-derecha",
      "category": "sustantivo",
      "source": "dia-05-pesn-partizan",
      "day": 5,
      "title": "Песнь Партизан / Le Chant des Partisans",
      "filePath": "src/content/blog/dia-05-pesn-partizan.md",
      "lessons": [
        5,
        6,
        8,
        11
      ],
      "frequency": 4,
      "firstAppearance": 5
    },
    {
      "id": "antifascista-antifascist",
      "es": "antifascista",
      "en": "antifascist",
      "de": "Antifaschist",
      "pt": "antifascista",
      "ru": "антифашист",
      "ruRom": "antifashist",
      "zh": "反法西斯",
      "zhPinyin": "fǎn fǎxīsī",
      "zhStrokes": "16",
      "zhRadical": "反 (opuesto)",
      "zhStructure": "izquierda-derecha",
      "category": "adjetivo",
      "source": "dia-05-pesn-partizan",
      "day": 5,
      "title": "Песнь Партизан / Le Chant des Partisans",
      "filePath": "src/content/blog/dia-05-pesn-partizan.md",
      "lessons": [
        5,
        6,
        11
      ],
      "frequency": 3,
      "firstAppearance": 5
    },
    {
      "id": "combatientes-fighters",
      "es": "combatientes",
      "en": "fighters",
      "de": "Kämpfer",
      "pt": "combatentes",
      "ru": "бойцы",
      "ruRom": "boytsy",
      "zh": "战士",
      "zhPinyin": "zhànshì",
      "zhStrokes": "10",
      "zhRadical": "戈 (lanza)",
      "zhStructure": "izquierda-derecha",
      "category": "sustantivo",
      "source": "dia-05-pesn-partizan",
      "day": 5,
      "title": "Песнь Партизан / Le Chant des Partisans",
      "filePath": "src/content/blog/dia-05-pesn-partizan.md",
      "lessons": [
        5
      ],
      "frequency": 1,
      "firstAppearance": 5
    },
    {
      "id": "enemigo-enemy",
      "es": "enemigo",
      "en": "enemy",
      "de": "Feind",
      "pt": "inimigo",
      "ru": "враг",
      "ruRom": "vrag",
      "zh": "敌人",
      "zhPinyin": "dírén",
      "zhStrokes": "6",
      "zhRadical": "攴 (golpear)",
      "zhStructure": "izquierda-derecha",
      "category": "sustantivo",
      "source": "dia-05-pesn-partizan",
      "day": 5,
      "title": "Песнь Партизан / Le Chant des Partisans",
      "filePath": "src/content/blog/dia-05-pesn-partizan.md",
      "lessons": [
        5
      ],
      "frequency": 1,
      "firstAppearance": 5
    },
    {
      "id": "patria-homeland",
      "es": "patria",
      "en": "homeland",
      "de": "Vaterland",
      "pt": "pátria",
      "ru": "родина",
      "ruRom": "rodina",
      "zh": "祖国",
      "zhPinyin": "zǔguó",
      "zhStrokes": "14",
      "zhRadical": "示 (sagrado)",
      "zhStructure": "izquierda-derecha",
      "category": "sustantivo",
      "source": "dia-05-pesn-partizan",
      "day": 5,
      "title": "Песнь Партизан / Le Chant des Partisans",
      "filePath": "src/content/blog/dia-05-pesn-partizan.md",
      "lessons": [
        5,
        8
      ],
      "frequency": 2,
      "firstAppearance": 5
    },
    {
      "id": "secreto-secret",
      "es": "secreto",
      "en": "secret",
      "de": "heimlich",
      "pt": "secreto",
      "ru": "тайный",
      "ruRom": "taynyy",
      "zh": "秘密的",
      "zhPinyin": "mìmì de",
      "zhStrokes": "21",
      "zhRadical": "禾 (cereal) + 宀 (techo)",
      "zhStructure": "compuesto",
      "category": "adjetivo",
      "source": "dia-06-der-heimliche-aufmarsch",
      "day": 6,
      "title": "Der Heimliche Aufmarsch",
      "filePath": "src/content/blog/dia-06-der-heimliche-aufmarsch.md",
      "lessons": [
        6
      ],
      "frequency": 1,
      "firstAppearance": 6
    },
    {
      "id": "susurro-whisper",
      "es": "susurro",
      "en": "whisper",
      "de": "Geflüster",
      "pt": "sussurro",
      "ru": "шёпот",
      "ruRom": "shyopot",
      "zh": "窃窃私语",
      "zhPinyin": "qièqiè sīyǔ",
      "zhStrokes": "31",
      "zhRadical": "穴 (cueva) + 禾 (cereal) + 言 (habla)",
      "zhStructure": "compuesto",
      "category": "sustantivo",
      "source": "dia-06-der-heimliche-aufmarsch",
      "day": 6,
      "title": "Der Heimliche Aufmarsch",
      "filePath": "src/content/blog/dia-06-der-heimliche-aufmarsch.md",
      "lessons": [
        6
      ],
      "frequency": 1,
      "firstAppearance": 6
    },
    {
      "id": "horda-saqueadora-robber-horde",
      "es": "horda saqueadora",
      "en": "robber horde",
      "de": "Räuberheer",
      "pt": "horda saqueadora",
      "ru": "разбойничья орда",
      "ruRom": "razboynichjya orda",
      "zh": "强盗军队",
      "zhPinyin": "qiángdào jūnduì",
      "zhStrokes": "20",
      "zhRadical": "弓 (arco) + 皿 (plato) + 冠 (corona)",
      "zhStructure": "compuesto",
      "category": "sustantivo",
      "source": "dia-06-der-heimliche-aufmarsch",
      "day": 6,
      "title": "Der Heimliche Aufmarsch",
      "filePath": "src/content/blog/dia-06-der-heimliche-aufmarsch.md",
      "lessons": [
        6
      ],
      "frequency": 1,
      "firstAppearance": 6
    },
    {
      "id": "escuchar-to-hear",
      "es": "escuchar",
      "en": "to hear",
      "de": "hören",
      "pt": "escutar",
      "ru": "слышать",
      "ruRom": "slyshat'",
      "zh": "听见",
      "zhPinyin": "tīngjiàn",
      "zhStrokes": "15",
      "zhRadical": "口 (boca) + 见 (ver)",
      "zhStructure": "compuesto",
      "category": "verbo",
      "source": "dia-06-der-heimliche-aufmarsch",
      "day": 6,
      "title": "Der Heimliche Aufmarsch",
      "filePath": "src/content/blog/dia-06-der-heimliche-aufmarsch.md",
      "lessons": [
        6
      ],
      "frequency": 1,
      "firstAppearance": 6
    },
    {
      "id": "ministro-de-guerra-war-minister",
      "es": "ministro de guerra",
      "en": "war minister",
      "de": "Kriegsminister",
      "pt": "ministro da guerra",
      "ru": "военный министр",
      "ruRom": "voyennyy ministr",
      "zh": "战争部长",
      "zhPinyin": "zhànzhēng bùzhǎng",
      "zhStrokes": "13",
      "zhRadical": "戈 (lanza)",
      "zhStructure": "izquierda-derecha",
      "category": "sustantivo",
      "source": "dia-06-der-heimliche-aufmarsch",
      "day": 6,
      "title": "Der Heimliche Aufmarsch",
      "filePath": "src/content/blog/dia-06-der-heimliche-aufmarsch.md",
      "lessons": [
        6
      ],
      "frequency": 1,
      "firstAppearance": 6
    },
    {
      "id": "luz-sovi-tica-soviet-light",
      "es": "luz soviética",
      "en": "Soviet light",
      "de": "Sowjetlicht",
      "pt": "luz soviética",
      "ru": "советский свет",
      "ruRom": "sovetskiy svet",
      "zh": "苏维埃之光",
      "zhPinyin": "Sūwéi'āi zhī guāng",
      "zhStrokes": "18",
      "zhRadical": "艹 (hierba) + 止 (parar) + 日 (sol)",
      "zhStructure": "compuesto",
      "category": "sustantivo",
      "source": "dia-06-der-heimliche-aufmarsch",
      "day": 6,
      "title": "Der Heimliche Aufmarsch",
      "filePath": "src/content/blog/dia-06-der-heimliche-aufmarsch.md",
      "lessons": [
        6
      ],
      "frequency": 1,
      "firstAppearance": 6
    },
    {
      "id": "rep-blica-mundial-world-republic",
      "es": "república mundial",
      "en": "world republic",
      "de": "Weltrepublik",
      "pt": "república mundial",
      "ru": "мировая республика",
      "ruRom": "mirovaya respublika",
      "zh": "世界共和国",
      "zhPinyin": "shìjiè gònghéguó",
      "zhStrokes": "17",
      "zhRadical": "世 (generación) + 共 (junto)",
      "zhStructure": "compuesto",
      "category": "sustantivo",
      "source": "dia-06-der-heimliche-aufmarsch",
      "day": 6,
      "title": "Der Heimliche Aufmarsch",
      "filePath": "src/content/blog/dia-06-der-heimliche-aufmarsch.md",
      "lessons": [
        6
      ],
      "frequency": 1,
      "firstAppearance": 6
    },
    {
      "id": "oriente-east",
      "es": "oriente",
      "en": "east",
      "de": "Osten",
      "pt": "oriente",
      "ru": "восток",
      "ruRom": "vostok",
      "zh": "东方",
      "zhPinyin": "dōng fāng",
      "zhStrokes": "8",
      "zhRadical": "方 (dirección)",
      "zhStructure": "izquierda-derecha",
      "category": "sustantivo",
      "source": "dia-07-dongfang-hong",
      "day": 7,
      "title": "东方红 (Dōngfāng hóng)",
      "filePath": "src/content/blog/dia-07-dongfang-hong.md",
      "lessons": [
        7
      ],
      "frequency": 1,
      "firstAppearance": 7
    },
    {
      "id": "rojo-red",
      "es": "rojo",
      "en": "red",
      "de": "rot",
      "pt": "vermelho",
      "ru": "красный",
      "ruRom": "krasnyy",
      "zh": "红",
      "zhPinyin": "hóng",
      "zhStrokes": "6",
      "zhRadical": "纟 (seda)",
      "zhStructure": "izquierda-derecha",
      "category": "adjetivo",
      "source": "dia-07-dongfang-hong",
      "day": 7,
      "title": "东方红 (Dōngfāng hóng)",
      "filePath": "src/content/blog/dia-07-dongfang-hong.md",
      "lessons": [
        7
      ],
      "frequency": 1,
      "firstAppearance": 7
    },
    {
      "id": "sol-sun",
      "es": "sol",
      "en": "sun",
      "de": "Sonne",
      "pt": "sol",
      "ru": "солнце",
      "ruRom": "solntse",
      "zh": "太阳",
      "zhPinyin": "tài yáng",
      "zhStrokes": "10",
      "zhRadical": "日 (sol)",
      "zhStructure": "arriba-abajo",
      "category": "sustantivo",
      "source": "dia-07-dongfang-hong",
      "day": 7,
      "title": "东方红 (Dōngfāng hóng)",
      "filePath": "src/content/blog/dia-07-dongfang-hong.md",
      "lessons": [
        7
      ],
      "frequency": 1,
      "firstAppearance": 7
    },
    {
      "id": "salvador-savior",
      "es": "salvador",
      "en": "savior",
      "de": "Retter",
      "pt": "salvador",
      "ru": "спаситель",
      "ruRom": "spasitel'",
      "zh": "救星",
      "zhPinyin": "jiùxīng",
      "zhStrokes": "15",
      "zhRadical": "攵 (golpear) + 日 (sol)",
      "zhStructure": "compuesto",
      "category": "sustantivo",
      "source": "dia-07-dongfang-hong",
      "day": 7,
      "title": "东方红 (Dōngfāng hóng)",
      "filePath": "src/content/blog/dia-07-dongfang-hong.md",
      "lessons": [
        7
      ],
      "frequency": 1,
      "firstAppearance": 7
    },
    {
      "id": "surgir-to-rise",
      "es": "surgir",
      "en": "to rise",
      "de": "aufgehen",
      "pt": "nascer",
      "ru": "восходить",
      "ruRom": "voskhodit'",
      "zh": "升起",
      "zhPinyin": "shēngqǐ",
      "zhStrokes": "8",
      "zhRadical": "十 (diez) + 辶 (caminar)",
      "zhStructure": "compuesto",
      "category": "verbo",
      "source": "dia-07-dongfang-hong",
      "day": 7,
      "title": "东方红 (Dōngfāng hóng)",
      "filePath": "src/content/blog/dia-07-dongfang-hong.md",
      "lessons": [
        7
      ],
      "frequency": 1,
      "firstAppearance": 7
    },
    {
      "id": "aparecer-to-appear",
      "es": "aparecer",
      "en": "to appear",
      "de": "erscheinen",
      "pt": "aparecer",
      "ru": "появляться",
      "ruRom": "poyavlyat'sya",
      "zh": "出现",
      "zhPinyin": "chūxiàn",
      "zhStrokes": "11",
      "zhRadical": "凵 (recipiente) + 王 (rey)",
      "zhStructure": "compuesto",
      "category": "verbo",
      "source": "dia-07-dongfang-hong",
      "day": 7,
      "title": "东方红 (Dōngfāng hóng)",
      "filePath": "src/content/blog/dia-07-dongfang-hong.md",
      "lessons": [
        7
      ],
      "frequency": 1,
      "firstAppearance": 7
    },
    {
      "id": "l-der-leader",
      "es": "líder",
      "en": "leader",
      "de": "Führer",
      "pt": "líder",
      "ru": "лидер",
      "ruRom": "lider",
      "zh": "领袖",
      "zhPinyin": "lǐngxiù",
      "zhStrokes": "17",
      "zhRadical": "页 (página) + 衣 (ropa)",
      "zhStructure": "compuesto",
      "category": "sustantivo",
      "source": "dia-07-dongfang-hong",
      "day": 7,
      "title": "东方红 (Dōngfāng hóng)",
      "filePath": "src/content/blog/dia-07-dongfang-hong.md",
      "lessons": [
        7
      ],
      "frequency": 1,
      "firstAppearance": 7
    },
    {
      "id": "grande-great",
      "es": "grande",
      "en": "great",
      "de": "groß",
      "pt": "grande",
      "ru": "великий",
      "ruRom": "velikiy",
      "zh": "伟大",
      "zhPinyin": "wěi dà",
      "zhStrokes": "9",
      "zhRadical": "亻 (persona) + 大 (grande)",
      "zhStructure": "izquierda-derecha",
      "category": "adjetivo",
      "source": "dia-07-dongfang-hong",
      "day": 7,
      "title": "东方红 (Dōngfāng hóng)",
      "filePath": "src/content/blog/dia-07-dongfang-hong.md",
      "lessons": [
        7
      ],
      "frequency": 1,
      "firstAppearance": 7
    },
    {
      "id": "presidente-chairman",
      "es": "presidente",
      "en": "chairman",
      "de": "Vorsitzender",
      "pt": "presidente",
      "ru": "председатель",
      "ruRom": "predsedatel'",
      "zh": "主席",
      "zhPinyin": "zhǔxí",
      "zhStrokes": "6",
      "zhRadical": "主 (señor)",
      "zhStructure": "arriba-abajo",
      "category": "sustantivo",
      "source": "dia-07-dongfang-hong",
      "day": 7,
      "title": "东方红 (Dōngfāng hóng)",
      "filePath": "src/content/blog/dia-07-dongfang-hong.md",
      "lessons": [
        7
      ],
      "frequency": 1,
      "firstAppearance": 7
    },
    {
      "id": "partido-comunista-communist-party",
      "es": "partido comunista",
      "en": "communist party",
      "de": "Kommunistische Partei",
      "pt": "partido comunista",
      "ru": "коммунистическая партия",
      "ruRom": "kommunisticheskaya partiya",
      "zh": "共产党",
      "zhPinyin": "gòngchǎndǎng",
      "zhStrokes": "20",
      "zhRadical": "八 (ocho) + 文 (cultura) + 子 (hijo)",
      "zhStructure": "compuesto",
      "category": "sustantivo",
      "source": "dia-07-dongfang-hong",
      "day": 7,
      "title": "东方红 (Dōngfāng hóng)",
      "filePath": "src/content/blog/dia-07-dongfang-hong.md",
      "lessons": [
        7
      ],
      "frequency": 1,
      "firstAppearance": 7
    },
    {
      "id": "sagrada-sacred",
      "es": "sagrada",
      "en": "sacred",
      "de": "heilig",
      "pt": "sagrada",
      "ru": "священная",
      "ruRom": "svyashchennaya",
      "zh": "神圣的",
      "zhPinyin": "shénshèng de",
      "zhStrokes": "13",
      "zhRadical": "示 (mostrar)",
      "zhStructure": "izquierda-derecha",
      "category": "adjetivo",
      "source": "dia-08-the-sacred-war",
      "day": 8,
      "title": "Священная война",
      "filePath": "src/content/blog/dia-08-the-sacred-war.md",
      "lessons": [
        8
      ],
      "frequency": 1,
      "firstAppearance": 8
    },
    {
      "id": "heroico-heroic",
      "es": "heroico",
      "en": "heroic",
      "de": "heldenhaft",
      "pt": "heroico",
      "ru": "героический",
      "ruRom": "geroyicheskiy",
      "zh": "英勇的",
      "zhPinyin": "yīngyǒng de",
      "zhStrokes": "13",
      "zhRadical": "艹 (hierba)",
      "zhStructure": "arriba-abajo",
      "category": "adjetivo",
      "source": "dia-08-the-sacred-war",
      "day": 8,
      "title": "Священная война",
      "filePath": "src/content/blog/dia-08-the-sacred-war.md",
      "lessons": [
        8
      ],
      "frequency": 1,
      "firstAppearance": 8
    },
    {
      "id": "invasi-n-invasion",
      "es": "invasión",
      "en": "invasion",
      "de": "Invasion",
      "pt": "invasão",
      "ru": "вторжение",
      "ruRom": "vtorzheniye",
      "zh": "入侵",
      "zhPinyin": "rùqīn",
      "zhStrokes": "8",
      "zhRadical": "入 (entrar)",
      "zhStructure": "izquierda-derecha",
      "category": "sustantivo",
      "source": "dia-08-the-sacred-war",
      "day": 8,
      "title": "Священная война",
      "filePath": "src/content/blog/dia-08-the-sacred-war.md",
      "lessons": [
        8
      ],
      "frequency": 1,
      "firstAppearance": 8
    },
    {
      "id": "defensa-defense",
      "es": "defensa",
      "en": "defense",
      "de": "Verteidigung",
      "pt": "defesa",
      "ru": "оборона",
      "ruRom": "oborona",
      "zh": "防御",
      "zhPinyin": "fáng yù",
      "zhStrokes": "11",
      "zhRadical": "阝 (montículo) + 彳 (caminar)",
      "zhStructure": "compuesto",
      "category": "sustantivo",
      "source": "dia-08-the-sacred-war",
      "day": 8,
      "title": "Священная война",
      "filePath": "src/content/blog/dia-08-the-sacred-war.md",
      "lessons": [
        8
      ],
      "frequency": 1,
      "firstAppearance": 8
    },
    {
      "id": "asedio-leningrado-siege-of-leningrad",
      "es": "asedio Leningrado",
      "en": "Siege of Leningrad",
      "de": "Belagerung Leningrads",
      "pt": "cerco de Leningrado",
      "ru": "блокада Ленинграда",
      "ruRom": "blokada Leningrada",
      "zh": "列宁格勒围城",
      "zhPinyin": "Lièníngélè wéichéng",
      "zhStrokes": "35",
      "zhRadical": "列 (enumerar)",
      "zhStructure": "compuesto",
      "category": "sustantivo",
      "source": "dia-08-the-sacred-war",
      "day": 8,
      "title": "Священная война",
      "filePath": "src/content/blog/dia-08-the-sacred-war.md",
      "lessons": [
        8
      ],
      "frequency": 1,
      "firstAppearance": 8
    },
    {
      "id": "frente-oriental-eastern-front",
      "es": "frente oriental",
      "en": "Eastern Front",
      "de": "Ostfront",
      "pt": "frente oriental",
      "ru": "Восточный фронт",
      "ruRom": "Vostochnyy front",
      "zh": "东线战场",
      "zhPinyin": "dōngxiàn zhànchǎng",
      "zhStrokes": "22",
      "zhRadical": "东 (este)",
      "zhStructure": "compuesto",
      "category": "sustantivo",
      "source": "dia-08-the-sacred-war",
      "day": 8,
      "title": "Священная война",
      "filePath": "src/content/blog/dia-08-the-sacred-war.md",
      "lessons": [
        8
      ],
      "frequency": 1,
      "firstAppearance": 8
    },
    {
      "id": "mil-novecientos-cuarenta-y-uno-nineteen-forty-one",
      "es": "mil novecientos cuarenta y uno",
      "en": "nineteen forty-one",
      "de": "neunzehnhunderteinundvierzig",
      "pt": "mil novecentos e quarenta e um",
      "ru": "тысяча девятьсот сорок один",
      "ruRom": "tysyacha devyat'sot sorok odin",
      "zh": "一九四一年",
      "zhPinyin": "yījiǔsìyī nián",
      "category": "sustantivo",
      "source": "dia-08-the-sacred-war",
      "day": 8,
      "title": "Священная война",
      "filePath": "src/content/blog/dia-08-the-sacred-war.md",
      "lessons": [
        8
      ],
      "frequency": 1,
      "firstAppearance": 8
    },
    {
      "id": "opresi-n-oppression",
      "es": "opresión",
      "en": "oppression",
      "de": "Unterdrückung",
      "pt": "opressão",
      "ru": "угнетение",
      "ruRom": "ugneteniye",
      "zh": "压迫",
      "zhPinyin": "yā pò",
      "zhStrokes": "16",
      "zhRadical": "土 (tierra) + 白 (blanco)",
      "zhStructure": "compuesto",
      "category": "sustantivo",
      "source": "dia-09-hijos-del-pueblo",
      "day": 9,
      "title": "Hijos del pueblo",
      "filePath": "src/content/blog/dia-09-hijos-del-pueblo.md",
      "lessons": [
        9
      ],
      "frequency": 1,
      "firstAppearance": 9
    },
    {
      "id": "hijos-children",
      "es": "hijos",
      "en": "children",
      "de": "Kinder",
      "pt": "filhos",
      "ru": "дети",
      "ruRom": "deti",
      "zh": "孩子们",
      "zhPinyin": "háizi men",
      "zhStrokes": "18",
      "zhRadical": "子 (hijo) + 亻 (persona)",
      "zhStructure": "compuesto",
      "category": "sustantivo",
      "source": "dia-09-hijos-del-pueblo",
      "day": 9,
      "title": "Hijos del pueblo",
      "filePath": "src/content/blog/dia-09-hijos-del-pueblo.md",
      "lessons": [
        9
      ],
      "frequency": 1,
      "firstAppearance": 9
    },
    {
      "id": "igualdad-equality",
      "es": "igualdad",
      "en": "equality",
      "de": "Gleichheit",
      "pt": "igualdade",
      "ru": "равенство",
      "ruRom": "ravenstvo",
      "zh": "平等",
      "zhPinyin": "píng děng",
      "zhStrokes": "10",
      "zhRadical": "干 (seco) + 竹 (bambú)",
      "zhStructure": "compuesto",
      "category": "sustantivo",
      "source": "dia-09-hijos-del-pueblo",
      "day": 9,
      "title": "Hijos del pueblo",
      "filePath": "src/content/blog/dia-09-hijos-del-pueblo.md",
      "lessons": [
        9
      ],
      "frequency": 1,
      "firstAppearance": 9
    },
    {
      "id": "trabajadores-workers",
      "es": "trabajadores",
      "en": "workers",
      "de": "Arbeiter",
      "pt": "trabalhadores",
      "ru": "рабочие",
      "ruRom": "rabochiye",
      "zh": "工人",
      "zhPinyin": "gōngrén",
      "zhStrokes": "7",
      "zhRadical": "工 (trabajo)",
      "zhStructure": "izquierda-derecha",
      "category": "sustantivo",
      "source": "dia-09-hijos-del-pueblo",
      "day": 9,
      "title": "Hijos del pueblo",
      "filePath": "src/content/blog/dia-09-hijos-del-pueblo.md",
      "lessons": [
        9,
        10
      ],
      "frequency": 2,
      "firstAppearance": 9
    },
    {
      "id": "compa-eros-comrades",
      "es": "compañeros",
      "en": "comrades",
      "de": "Genossen",
      "pt": "companheiros",
      "ru": "товарищи",
      "ruRom": "tovarishchi",
      "zh": "同志",
      "zhPinyin": "tóngzhì",
      "zhStrokes": "14",
      "zhRadical": "口 (boca) + 心 (corazón)",
      "zhStructure": "compuesto",
      "category": "sustantivo",
      "source": "dia-09-hijos-del-pueblo",
      "day": 9,
      "title": "Hijos del pueblo",
      "filePath": "src/content/blog/dia-09-hijos-del-pueblo.md",
      "lessons": [
        9
      ],
      "frequency": 1,
      "firstAppearance": 9
    },
    {
      "id": "primera-internacional-first-international",
      "es": "Primera Internacional",
      "en": "First International",
      "de": "Erste Internationale",
      "pt": "Primeira Internacional",
      "ru": "Первый Интернационал",
      "ruRom": "Pervyy Internatsional",
      "zh": "第一国际",
      "zhPinyin": "dì-yī guójì",
      "zhStrokes": "16",
      "zhRadical": "囗 (recinto)",
      "zhStructure": "encierro",
      "category": "sustantivo",
      "source": "dia-09-hijos-del-pueblo",
      "day": 9,
      "title": "Hijos del pueblo",
      "filePath": "src/content/blog/dia-09-hijos-del-pueblo.md",
      "lessons": [
        9
      ],
      "frequency": 1,
      "firstAppearance": 9
    },
    {
      "id": "huelga-general-general-strike",
      "es": "huelga general",
      "en": "general strike",
      "de": "Generalstreik",
      "pt": "greve geral",
      "ru": "всеобщая забастовка",
      "ruRom": "vseobshchaya zabastovka",
      "zh": "总罢工",
      "zhPinyin": "zǒng bàgōng",
      "zhStrokes": "18",
      "zhRadical": "总 (total) + 工 (trabajo)",
      "zhStructure": "compuesto",
      "category": "sustantivo",
      "source": "dia-09-hijos-del-pueblo",
      "day": 9,
      "title": "Hijos del pueblo",
      "filePath": "src/content/blog/dia-09-hijos-del-pueblo.md",
      "lessons": [
        9
      ],
      "frequency": 1,
      "firstAppearance": 9
    },
    {
      "id": "sindicalismo-syndicalism",
      "es": "sindicalismo",
      "en": "syndicalism",
      "de": "Syndikalismus",
      "pt": "sindicalismo",
      "ru": "синдикализм",
      "ruRom": "sindikalizm",
      "zh": "工团主义",
      "zhPinyin": "gōngtuán zhǔyì",
      "zhStrokes": "17",
      "zhRadical": "工 (trabajo) + 囗 (recinto) + 主 (señor)",
      "zhStructure": "compuesto",
      "category": "sustantivo",
      "source": "dia-09-hijos-del-pueblo",
      "day": 9,
      "title": "Hijos del pueblo",
      "filePath": "src/content/blog/dia-09-hijos-del-pueblo.md",
      "lessons": [
        9
      ],
      "frequency": 1,
      "firstAppearance": 9
    },
    {
      "id": "mil-ochocientos-ochenta-y-cinco-eighteen-eighty-five",
      "es": "mil ochocientos ochenta y cinco",
      "en": "eighteen eighty-five",
      "de": "achtzehnhundertfünfundachtzig",
      "pt": "mil oitocentos e oitenta e cinco",
      "ru": "тысяча восемьсот восемьдесят пять",
      "ruRom": "tysyacha vosem'sot vosem'desyat pyat'",
      "zh": "一八八五年",
      "zhPinyin": "yībābāwǔ nián",
      "category": "sustantivo",
      "source": "dia-09-hijos-del-pueblo",
      "day": 9,
      "title": "Hijos del pueblo",
      "filePath": "src/content/blog/dia-09-hijos-del-pueblo.md",
      "lessons": [
        9
      ],
      "frequency": 1,
      "firstAppearance": 9
    },
    {
      "id": "necio-foolish",
      "es": "necio",
      "en": "foolish",
      "de": "töricht",
      "pt": "tolo",
      "ru": "глупый",
      "ruRom": "glupyy",
      "zh": "愚蠢",
      "zhPinyin": "yúchǔn",
      "zhStrokes": "13",
      "zhRadical": "心 (corazón)",
      "zhStructure": "arriba-abajo",
      "category": "adjetivo",
      "source": "dia-10-oy-ir-narishe-tsienistn",
      "day": 10,
      "title": "Oy, Ir Narishe Tsienistn",
      "filePath": "src/content/blog/dia-10-oy-ir-narishe-tsienistn.md",
      "lessons": [
        10
      ],
      "frequency": 1,
      "firstAppearance": 10
    },
    {
      "id": "fantasear-fantasize",
      "es": "fantasear",
      "en": "fantasize",
      "de": "phantasieren",
      "pt": "fantasiar",
      "ru": "фантазировать",
      "ruRom": "fantazirovat'",
      "zh": "幻想",
      "zhPinyin": "huànxiǎng",
      "zhStrokes": "11",
      "zhRadical": "幺 (pequeño) + 心 (corazón)",
      "zhStructure": "compuesto",
      "category": "verbo",
      "source": "dia-10-oy-ir-narishe-tsienistn",
      "day": 10,
      "title": "Oy, Ir Narishe Tsienistn",
      "filePath": "src/content/blog/dia-10-oy-ir-narishe-tsienistn.md",
      "lessons": [
        10
      ],
      "frequency": 1,
      "firstAppearance": 10
    },
    {
      "id": "perecer-perish",
      "es": "perecer",
      "en": "perish",
      "de": "verderben",
      "pt": "perecer",
      "ru": "гибнуть",
      "ruRom": "gibnut'",
      "zh": "灭亡",
      "zhPinyin": "miè wáng",
      "zhStrokes": "10",
      "zhRadical": "火 (fuego) + 亡 (muerte)",
      "zhStructure": "compuesto",
      "category": "verbo",
      "source": "dia-10-oy-ir-narishe-tsienistn",
      "day": 10,
      "title": "Oy, Ir Narishe Tsienistn",
      "filePath": "src/content/blog/dia-10-oy-ir-narishe-tsienistn.md",
      "lessons": [
        10
      ],
      "frequency": 1,
      "firstAppearance": 10
    },
    {
      "id": "juventud-youth",
      "es": "juventud",
      "en": "youth",
      "de": "Jugend",
      "pt": "juventude",
      "ru": "молодежь",
      "ruRom": "molodyozh",
      "zh": "青年",
      "zhPinyin": "qīngnián",
      "zhStrokes": "11",
      "zhRadical": "青 (azul) + 彡 (adorno)",
      "zhStructure": "compuesto",
      "category": "sustantivo",
      "source": "dia-10-oy-ir-narishe-tsienistn",
      "day": 10,
      "title": "Oy, Ir Narishe Tsienistn",
      "filePath": "src/content/blog/dia-10-oy-ir-narishe-tsienistn.md",
      "lessons": [
        10
      ],
      "frequency": 1,
      "firstAppearance": 10
    },
    {
      "id": "uni-n-union",
      "es": "unión",
      "en": "union",
      "de": "Verband",
      "pt": "união",
      "ru": "союз",
      "ruRom": "soyuz",
      "zh": "联盟",
      "zhPinyin": "lián méng",
      "zhStrokes": "25",
      "zhRadical": "耳 (oreja)",
      "zhStructure": "compuesto",
      "category": "sustantivo",
      "source": "dia-10-oy-ir-narishe-tsienistn",
      "day": 10,
      "title": "Oy, Ir Narishe Tsienistn",
      "filePath": "src/content/blog/dia-10-oy-ir-narishe-tsienistn.md",
      "lessons": [
        10
      ],
      "frequency": 1,
      "firstAppearance": 10
    },
    {
      "id": "di-spora-diaspora",
      "es": "diáspora",
      "en": "diaspora",
      "de": "Diaspora",
      "pt": "diáspora",
      "ru": "диаспора",
      "ruRom": "diaspora",
      "zh": "散居",
      "zhPinyin": "sànjū",
      "zhStrokes": "16",
      "zhRadical": "攵 (golpear) + 尸 (cuerpo)",
      "zhStructure": "compuesto",
      "category": "sustantivo",
      "source": "dia-10-oy-ir-narishe-tsienistn",
      "day": 10,
      "title": "Oy, Ir Narishe Tsienistn",
      "filePath": "src/content/blog/dia-10-oy-ir-narishe-tsienistn.md",
      "lessons": [
        10
      ],
      "frequency": 1,
      "firstAppearance": 10
    },
    {
      "id": "proletario-proletarian",
      "es": "proletario",
      "en": "proletarian",
      "de": "Proletarier",
      "pt": "proletário",
      "ru": "пролетарий",
      "ruRom": "proletariy",
      "zh": "无产者",
      "zhPinyin": "wúchǎnzhě",
      "zhStrokes": "11",
      "zhRadical": "无 (nada) + 文 (cultura) + 者 (persona)",
      "zhStructure": "compuesto",
      "category": "sustantivo",
      "source": "dia-10-oy-ir-narishe-tsienistn",
      "day": 10,
      "title": "Oy, Ir Narishe Tsienistn",
      "filePath": "src/content/blog/dia-10-oy-ir-narishe-tsienistn.md",
      "lessons": [
        10,
        11
      ],
      "frequency": 2,
      "firstAppearance": 10
    },
    {
      "id": "antisemitismo-antisemitism",
      "es": "antisemitismo",
      "en": "antisemitism",
      "de": "Antisemitismus",
      "pt": "antissemitismo",
      "ru": "антисемитизм",
      "ruRom": "antisemitizm",
      "zh": "反犹主义",
      "zhPinyin": "fǎn yóu zhǔyì",
      "zhStrokes": "12",
      "zhRadical": "又 (otra vez) + 犭 (perro) + 主 (señor)",
      "zhStructure": "compuesto",
      "category": "sustantivo",
      "source": "dia-10-oy-ir-narishe-tsienistn",
      "day": 10,
      "title": "Oy, Ir Narishe Tsienistn",
      "filePath": "src/content/blog/dia-10-oy-ir-narishe-tsienistn.md",
      "lessons": [
        10
      ],
      "frequency": 1,
      "firstAppearance": 10
    },
    {
      "id": "frente-front",
      "es": "frente",
      "en": "front",
      "de": "Front",
      "pt": "frente",
      "ru": "фронт",
      "ruRom": "front",
      "zh": "前线",
      "zhPinyin": "qiánxiàn",
      "zhStrokes": "9",
      "zhRadical": "前 (delante)",
      "zhStructure": "arriba-abajo",
      "category": "sustantivo",
      "source": "dia-11-einheitsfrontlied",
      "day": 11,
      "title": "Einheitsfrontlied",
      "filePath": "src/content/blog/dia-11-einheitsfrontlied.md",
      "lessons": [
        11
      ],
      "frequency": 1,
      "firstAppearance": 11
    },
    {
      "id": "comunista-communist",
      "es": "comunista",
      "en": "communist",
      "de": "Kommunist",
      "pt": "comunista",
      "ru": "коммунист",
      "ruRom": "kommunist",
      "zh": "共产主义者",
      "zhPinyin": "gòngchǎn zhǔyì zhě",
      "zhStrokes": "16",
      "zhRadical": "共 (junto)",
      "zhStructure": "compuesto",
      "category": "sustantivo",
      "source": "dia-11-einheitsfrontlied",
      "day": 11,
      "title": "Einheitsfrontlied",
      "filePath": "src/content/blog/dia-11-einheitsfrontlied.md",
      "lessons": [
        11
      ],
      "frequency": 1,
      "firstAppearance": 11
    },
    {
      "id": "socialista-socialist",
      "es": "socialista",
      "en": "socialist",
      "de": "Sozialist",
      "pt": "socialista",
      "ru": "социалист",
      "ruRom": "sotsialist",
      "zh": "社会主义者",
      "zhPinyin": "shèhuì zhǔyì zhě",
      "zhStrokes": "16",
      "zhRadical": "示 (mostrar)",
      "zhStructure": "compuesto",
      "category": "sustantivo",
      "source": "dia-11-einheitsfrontlied",
      "day": 11,
      "title": "Einheitsfrontlied",
      "filePath": "src/content/blog/dia-11-einheitsfrontlied.md",
      "lessons": [
        11
      ],
      "frequency": 1,
      "firstAppearance": 11
    },
    {
      "id": "mil-novecientos-treinta-y-cuatro-nineteen-thirty-four",
      "es": "mil novecientos treinta y cuatro",
      "en": "nineteen thirty-four",
      "de": "neunzehnhundertvierunddreißig",
      "pt": "mil novecentos e trinta e quatro",
      "ru": "тысяча девятьсот тридцать четыре",
      "ruRom": "tysyacha devyat'sot tridtsat' chetyre",
      "zh": "一九三四年",
      "zhPinyin": "yījiǔsānsì nián",
      "category": "sustantivo",
      "source": "dia-11-einheitsfrontlied",
      "day": 11,
      "title": "Einheitsfrontlied",
      "filePath": "src/content/blog/dia-11-einheitsfrontlied.md",
      "lessons": [
        11
      ],
      "frequency": 1,
      "firstAppearance": 11
    },
    {
      "id": "jornalero-farmhand",
      "es": "jornalero",
      "en": "farmhand",
      "de": "Landarbeiter",
      "pt": "jornaleiro",
      "ru": "батрак",
      "ruRom": "batrak",
      "zh": "雇农",
      "zhPinyin": "gùnóng",
      "zhStrokes": "12",
      "zhRadical": "雇 (emplear)",
      "zhStructure": "izquierda-derecha",
      "category": "sustantivo",
      "source": "dia-12-en-la-plaza-de-mi-pueblo",
      "day": 12,
      "title": "En la Plaza de mi Pueblo",
      "filePath": "src/content/blog/dia-12-en-la-plaza-de-mi-pueblo.md",
      "lessons": [
        12
      ],
      "frequency": 1,
      "firstAppearance": 12
    },
    {
      "id": "amo-master",
      "es": "amo",
      "en": "master",
      "de": "Herr",
      "pt": "patrão",
      "ru": "хозяин",
      "ruRom": "khozyain",
      "zh": "地主",
      "zhPinyin": "dìzhǔ",
      "zhStrokes": "8",
      "zhRadical": "土 (tierra)",
      "zhStructure": "arriba-abajo",
      "category": "sustantivo",
      "source": "dia-12-en-la-plaza-de-mi-pueblo",
      "day": 12,
      "title": "En la Plaza de mi Pueblo",
      "filePath": "src/content/blog/dia-12-en-la-plaza-de-mi-pueblo.md",
      "lessons": [
        12
      ],
      "frequency": 1,
      "firstAppearance": 12
    },
    {
      "id": "pu-o-fist",
      "es": "puño",
      "en": "fist",
      "de": "Faust",
      "pt": "punho",
      "ru": "кулак",
      "ruRom": "kulak",
      "zh": "拳头",
      "zhPinyin": "quántou",
      "zhStrokes": "13",
      "zhRadical": "手 (mano)",
      "zhStructure": "arriba-abajo",
      "category": "sustantivo",
      "source": "dia-12-en-la-plaza-de-mi-pueblo",
      "day": 12,
      "title": "En la Plaza de mi Pueblo",
      "filePath": "src/content/blog/dia-12-en-la-plaza-de-mi-pueblo.md",
      "lessons": [
        12
      ],
      "frequency": 1,
      "firstAppearance": 12
    },
    {
      "id": "levantado-raised",
      "es": "levantado",
      "en": "raised",
      "de": "erhoben",
      "pt": "levantado",
      "ru": "поднятый",
      "ruRom": "podnyatyy",
      "zh": "举起的",
      "zhPinyin": "jǔqǐ de",
      "zhStrokes": "12",
      "zhRadical": "手 (mano)",
      "zhStructure": "arriba-abajo",
      "category": "adjetivo",
      "source": "dia-12-en-la-plaza-de-mi-pueblo",
      "day": 12,
      "title": "En la Plaza de mi Pueblo",
      "filePath": "src/content/blog/dia-12-en-la-plaza-de-mi-pueblo.md",
      "lessons": [
        12
      ],
      "frequency": 1,
      "firstAppearance": 12
    },
    {
      "id": "tierra-land",
      "es": "tierra",
      "en": "land",
      "de": "Land",
      "pt": "terra",
      "ru": "земля",
      "ruRom": "zemlya",
      "zh": "土地",
      "zhPinyin": "tǔ dì",
      "zhStrokes": "6",
      "zhRadical": "土 (tierra)",
      "zhStructure": "izquierda-derecha",
      "category": "sustantivo",
      "source": "dia-12-en-la-plaza-de-mi-pueblo",
      "day": 12,
      "title": "En la Plaza de mi Pueblo",
      "filePath": "src/content/blog/dia-12-en-la-plaza-de-mi-pueblo.md",
      "lessons": [
        12
      ],
      "frequency": 1,
      "firstAppearance": 12
    },
    {
      "id": "sudor-sweat",
      "es": "sudor",
      "en": "sweat",
      "de": "Schweiß",
      "pt": "suor",
      "ru": "пот",
      "ruRom": "pot",
      "zh": "汗水",
      "zhPinyin": "hànshuǐ",
      "zhStrokes": "9",
      "zhRadical": "氵 (agua)",
      "zhStructure": "izquierda-derecha",
      "category": "sustantivo",
      "source": "dia-12-en-la-plaza-de-mi-pueblo",
      "day": 12,
      "title": "En la Plaza de mi Pueblo",
      "filePath": "src/content/blog/dia-12-en-la-plaza-de-mi-pueblo.md",
      "lessons": [
        12
      ],
      "frequency": 1,
      "firstAppearance": 12
    },
    {
      "id": "arado-plow",
      "es": "arado",
      "en": "plow",
      "de": "Pflug",
      "pt": "arado",
      "ru": "плуг",
      "ruRom": "plug",
      "zh": "犁",
      "zhPinyin": "lí",
      "zhStrokes": "11",
      "zhRadical": "牛 (buey)",
      "zhStructure": "arriba-abajo",
      "category": "sustantivo",
      "source": "dia-12-en-la-plaza-de-mi-pueblo",
      "day": 12,
      "title": "En la Plaza de mi Pueblo",
      "filePath": "src/content/blog/dia-12-en-la-plaza-de-mi-pueblo.md",
      "lessons": [
        12
      ],
      "frequency": 1,
      "firstAppearance": 12
    },
    {
      "id": "surcos-furrows",
      "es": "surcos",
      "en": "furrows",
      "de": "Furchen",
      "pt": "sulcos",
      "ru": "борозды",
      "ruRom": "borozdy",
      "zh": "沟垄",
      "zhPinyin": "gōulǒng",
      "zhStrokes": "10",
      "zhRadical": "氵 (agua)",
      "zhStructure": "izquierda-derecha",
      "category": "sustantivo",
      "source": "dia-12-en-la-plaza-de-mi-pueblo",
      "day": 12,
      "title": "En la Plaza de mi Pueblo",
      "filePath": "src/content/blog/dia-12-en-la-plaza-de-mi-pueblo.md",
      "lessons": [
        12
      ],
      "frequency": 1,
      "firstAppearance": 12
    },
    {
      "id": "compa-ero-comrade",
      "es": "compañero",
      "en": "comrade",
      "de": "Genosse",
      "pt": "companheiro",
      "ru": "товарищ",
      "ruRom": "tovarishch",
      "zh": "同志",
      "zhPinyin": "tóngzhì",
      "zhStrokes": "7",
      "zhRadical": "同 (mismo)",
      "zhStructure": "arriba-abajo",
      "category": "sustantivo",
      "source": "dia-12-en-la-plaza-de-mi-pueblo",
      "day": 12,
      "title": "En la Plaza de mi Pueblo",
      "filePath": "src/content/blog/dia-12-en-la-plaza-de-mi-pueblo.md",
      "lessons": [
        12
      ],
      "frequency": 1,
      "firstAppearance": 12
    },
    {
      "id": "trabajar-to-work",
      "es": "trabajar",
      "en": "to work",
      "de": "arbeiten",
      "pt": "trabalhar",
      "ru": "работать",
      "ruRom": "rabotat'",
      "zh": "劳作",
      "zhPinyin": "láozuò",
      "zhStrokes": "9",
      "zhRadical": "力 (fuerza)",
      "zhStructure": "izquierda-derecha",
      "category": "verbo",
      "source": "dia-12-en-la-plaza-de-mi-pueblo",
      "day": 12,
      "title": "En la Plaza de mi Pueblo",
      "filePath": "src/content/blog/dia-12-en-la-plaza-de-mi-pueblo.md",
      "lessons": [
        12
      ],
      "frequency": 1,
      "firstAppearance": 12
    },
    {
      "id": "regar-to-water",
      "es": "regar",
      "en": "to water",
      "de": "bewässern",
      "pt": "regar",
      "ru": "поливать",
      "ruRom": "polivat'",
      "zh": "浇灌",
      "zhPinyin": "jiāoguàn",
      "zhStrokes": "15",
      "zhRadical": "氵 (agua)",
      "zhStructure": "izquierda-derecha",
      "category": "verbo",
      "source": "dia-12-en-la-plaza-de-mi-pueblo",
      "day": 12,
      "title": "En la Plaza de mi Pueblo",
      "filePath": "src/content/blog/dia-12-en-la-plaza-de-mi-pueblo.md",
      "lessons": [
        12
      ],
      "frequency": 1,
      "firstAppearance": 12
    },
    {
      "id": "escribir-to-write",
      "es": "escribir",
      "en": "to write",
      "de": "schreiben",
      "pt": "escrever",
      "ru": "писать",
      "ruRom": "pisat'",
      "zh": "书写",
      "zhPinyin": "shūxiě",
      "zhStrokes": "9",
      "zhRadical": "乚 (segundo)",
      "zhStructure": "arriba-abajo",
      "category": "verbo",
      "source": "dia-12-en-la-plaza-de-mi-pueblo",
      "day": 12,
      "title": "En la Plaza de mi Pueblo",
      "filePath": "src/content/blog/dia-12-en-la-plaza-de-mi-pueblo.md",
      "lessons": [
        12
      ],
      "frequency": 1,
      "firstAppearance": 12
    },
    {
      "id": "miseria-misery",
      "es": "miseria",
      "en": "misery",
      "de": "Elend",
      "pt": "miséria",
      "ru": "нищета",
      "ruRom": "nishcheta",
      "zh": "痛苦",
      "zhPinyin": "tòngkǔ",
      "zhStrokes": "17",
      "zhRadical": "痛 (dolor)",
      "zhStructure": "arriba-abajo",
      "category": "sustantivo",
      "source": "dia-12-en-la-plaza-de-mi-pueblo",
      "day": 12,
      "title": "En la Plaza de mi Pueblo",
      "filePath": "src/content/blog/dia-12-en-la-plaza-de-mi-pueblo.md",
      "lessons": [
        12
      ],
      "frequency": 1,
      "firstAppearance": 12
    },
    {
      "id": "p-ginas-pages",
      "es": "páginas",
      "en": "pages",
      "de": "Seiten",
      "pt": "páginas",
      "ru": "страницы",
      "ruRom": "stranitsy",
      "zh": "篇章",
      "zhPinyin": "piānzhāng",
      "zhStrokes": "20",
      "zhRadical": "竹 (bambú)",
      "zhStructure": "arriba-abajo",
      "category": "sustantivo",
      "source": "dia-12-en-la-plaza-de-mi-pueblo",
      "day": 12,
      "title": "En la Plaza de mi Pueblo",
      "filePath": "src/content/blog/dia-12-en-la-plaza-de-mi-pueblo.md",
      "lessons": [
        12
      ],
      "frequency": 1,
      "firstAppearance": 12
    },
    {
      "id": "anarquista-anarchist",
      "es": "anarquista",
      "en": "anarchist",
      "de": "Anarchist",
      "pt": "anarquista",
      "ru": "анархист",
      "ruRom": "anarkhist",
      "zh": "无政府主义者",
      "zhPinyin": "wúzhèngfǔzhǔyìzhě",
      "zhStrokes": "23",
      "zhRadical": "政 (gobierno)",
      "zhStructure": "arriba-abajo",
      "category": "adjetivo",
      "source": "dia-12-en-la-plaza-de-mi-pueblo",
      "day": 12,
      "title": "En la Plaza de mi Pueblo",
      "filePath": "src/content/blog/dia-12-en-la-plaza-de-mi-pueblo.md",
      "lessons": [
        12
      ],
      "frequency": 1,
      "firstAppearance": 12
    },
    {
      "id": "rep-blica-republic",
      "es": "república",
      "en": "republic",
      "de": "Republik",
      "pt": "república",
      "ru": "республика",
      "ruRom": "respublika",
      "zh": "共和国",
      "zhPinyin": "gònghéguó",
      "zhStrokes": "14",
      "zhRadical": "八 (ocho)",
      "zhStructure": "izquierda-derecha",
      "category": "sustantivo",
      "source": "dia-12-en-la-plaza-de-mi-pueblo",
      "day": 12,
      "title": "En la Plaza de mi Pueblo",
      "filePath": "src/content/blog/dia-12-en-la-plaza-de-mi-pueblo.md",
      "lessons": [
        12
      ],
      "frequency": 1,
      "firstAppearance": 12
    },
    {
      "id": "comuna-commune",
      "es": "comuna",
      "en": "commune",
      "de": "Kommune",
      "pt": "comuna",
      "ru": "коммуна",
      "ruRom": "kommuna",
      "zh": "公社",
      "zhPinyin": "gōngshè",
      "zhStrokes": "10",
      "zhRadical": "八 (ocho)",
      "zhStructure": "izquierda-derecha",
      "category": "sustantivo",
      "source": "dia-12-en-la-plaza-de-mi-pueblo",
      "day": 12,
      "title": "En la Plaza de mi Pueblo",
      "filePath": "src/content/blog/dia-12-en-la-plaza-de-mi-pueblo.md",
      "lessons": [
        12
      ],
      "frequency": 1,
      "firstAppearance": 12
    }
  ]
}